cogs/setlang.py
cogs/Servermanament/autodelete.py
cogs/Servermanament/autorole.py
cogs/Servermanament/globalchat.py
cogs/Servermanament/levelsystem.py
cogs/Servermanament/logging.py
cogs/Servermanament/stats.py
cogs/Servermanament/tempvc.py
cogs/Servermanament/welcome.py
cogs/fun/__init__.py
cogs/fun/gewinnt.py
cogs/fun/tictactoe.py
cogs/fun/weather.py
cogs/fun/wikipedia/__init__.py
cogs/fun/wikipedia/autocomplete.py
cogs/fun/wikipedia/cache.py
cogs/fun/wikipedia/cog.py
cogs/fun/wikipedia/components.py
cogs/fun/wikipedia/config.py
cogs/fun/wikipedia/containers.py
cogs/fun/wikipedia/utils.py
cogs/informationen/botstatus.py
cogs/informationen/serverinfo.py
cogs/informationen/usermanagemt.py
cogs/moderation/antispam.py
cogs/moderation/moderation.py
cogs/moderation/notes.py
cogs/moderation/warningsystem.py
managerx/cli.py
managerx-2.2026.1.9.dist-info/licenses/LICENSE
managerx-2.2026.1.9.dist-info/METADATA
managerx-2.2026.1.9.dist-info/WHEEL
managerx-2.2026.1.9.dist-info/entry_points.txt
managerx-2.2026.1.9.dist-info/top_level.txt
managerx-2.2026.1.9.dist-info/RECORD
