Metadata-Version: 2.4
Name: ManagerX
Version: 2.2026.1.9
Summary: A powerful Discord bot for server management and fun.
Author-email: "OPPRO.NET Development" <development@oppro-network.de>, "OPPRO.NET Network" <contact@oppro-network.de>
License: GPL-3.0-or-later
Project-URL: Homepage, https://github.com/Oppro-net-Development/ManagerX
Project-URL: Documentation, https://docs.oppro-network.de/
Project-URL: Changelog, https://docs.oppro-network.de/en/latest/releases/index.html
Project-URL: BugTracker, https://github.com/Oppro-net-Development/ManagerX/issues
Classifier: Programming Language :: Python :: 3.8
Classifier: Programming Language :: Python :: 3.9
Classifier: Programming Language :: Python :: 3.10
Classifier: Programming Language :: Python :: 3.11
Classifier: License :: OSI Approved :: GNU General Public License v3 or later (GPLv3+)
Classifier: Operating System :: OS Independent
Requires-Python: >=3.8
License-File: LICENSE
Requires-Dist: ezcord==0.7.4
Requires-Dist: py-cord==2.7.0
Requires-Dist: aiosqlite==0.22.1
Requires-Dist: aiohttp==3.13.2
Requires-Dist: aiocache==0.12.3
Requires-Dist: propcache==0.4.1
Requires-Dist: requests==2.32.5
Requires-Dist: wikipedia==1.4.0
Requires-Dist: beautifulsoup4==4.14.3
Requires-Dist: soupsieve==2.8.1
Requires-Dist: yarl==1.22.0
Requires-Dist: frozenlist==1.8.0
Requires-Dist: h11==0.16.0
Requires-Dist: multidict==6.7.0
Requires-Dist: SimpleColoredLogs==1.3.0
Requires-Dist: FastAPI==0.100.0
Requires-Dist: uvicorn==0.24.0
Requires-Dist: Jinja2==3.1.6
Requires-Dist: MarkupSafe==3.0.3
Requires-Dist: starlette==0.50.0
Requires-Dist: timedelta==2020.12.3
Requires-Dist: ManagerX-Handler==1.0.4
Requires-Dist: ManagerX-DevTools==1.0.0
Provides-Extra: dev
Requires-Dist: python-dotenv==1.2.1; extra == "dev"
Requires-Dist: click==8.3.1; extra == "dev"
Requires-Dist: colorama==0.4.6; extra == "dev"
Requires-Dist: typing_extensions==4.15.0; extra == "dev"
Requires-Dist: typing-inspection==0.4.2; extra == "dev"
Requires-Dist: attrs==25.4.0; extra == "dev"
Requires-Dist: annotated-types==0.7.0; extra == "dev"
Requires-Dist: anyio==4.12.0; extra == "dev"
Requires-Dist: certifi==2025.11.12; extra == "dev"
Requires-Dist: charset-normalizer==3.4.4; extra == "dev"
Requires-Dist: idna==3.11; extra == "dev"
Requires-Dist: urllib3==2.6.2; extra == "dev"
Requires-Dist: build==1.3.0; extra == "dev"
Requires-Dist: twine==4.2.0; extra == "dev"
Provides-Extra: docs
Requires-Dist: sphinx<8,>=6; extra == "docs"
Requires-Dist: pydata-sphinx-theme; extra == "docs"
Requires-Dist: sphinx-autodoc-typehints; extra == "docs"
Requires-Dist: myst-parser<3,>=2; extra == "docs"
Requires-Dist: sphinx-copybutton; extra == "docs"
Provides-Extra: all
Requires-Dist: ezcord==0.7.4; extra == "all"
Requires-Dist: py-cord==2.7.0; extra == "all"
Requires-Dist: aiosqlite==0.22.1; extra == "all"
Requires-Dist: aiohttp==3.13.2; extra == "all"
Requires-Dist: aiocache==0.12.3; extra == "all"
Requires-Dist: propcache==0.4.1; extra == "all"
Requires-Dist: requests==2.32.5; extra == "all"
Requires-Dist: wikipedia==1.4.0; extra == "all"
Requires-Dist: beautifulsoup4==4.14.3; extra == "all"
Requires-Dist: soupsieve==2.8.1; extra == "all"
Requires-Dist: yarl==1.22.0; extra == "all"
Requires-Dist: frozenlist==1.8.0; extra == "all"
Requires-Dist: h11==0.16.0; extra == "all"
Requires-Dist: multidict==6.7.0; extra == "all"
Requires-Dist: python-dotenv==1.2.1; extra == "all"
Requires-Dist: click==8.3.1; extra == "all"
Requires-Dist: colorama==0.4.6; extra == "all"
Requires-Dist: typing_extensions==4.15.0; extra == "all"
Requires-Dist: typing-inspection==0.4.2; extra == "all"
Requires-Dist: attrs==25.4.0; extra == "all"
Requires-Dist: annotated-types==0.7.0; extra == "all"
Requires-Dist: anyio==4.12.0; extra == "all"
Requires-Dist: certifi==2025.11.12; extra == "all"
Requires-Dist: charset-normalizer==3.4.4; extra == "all"
Requires-Dist: idna==3.11; extra == "all"
Requires-Dist: urllib3==2.6.2; extra == "all"
Requires-Dist: Jinja2==3.1.6; extra == "all"
Requires-Dist: MarkupSafe==3.0.3; extra == "all"
Requires-Dist: starlette==0.50.0; extra == "all"
Requires-Dist: FastAPI==0.100.0; extra == "all"
Requires-Dist: uvicorn==0.24.0; extra == "all"
Requires-Dist: SimpleColoredLogs==1.3.0; extra == "all"
Requires-Dist: timedelta==2020.12.3; extra == "all"
Requires-Dist: sphinx<8,>=6; extra == "all"
Requires-Dist: pydata-sphinx-theme; extra == "all"
Requires-Dist: sphinx-autodoc-typehints; extra == "all"
Requires-Dist: myst-parser<3,>=2; extra == "all"
Requires-Dist: sphinx-copybutton; extra == "all"
Requires-Dist: build==1.3.0; extra == "all"
Requires-Dist: twine==4.2.0; extra == "all"
Dynamic: license-file
